deepmeta/__init__.py
deepmeta/maml.py
deepmeta/version.py
deepmeta-0.0.1.dist-info/METADATA
deepmeta-0.0.1.dist-info/WHEEL
deepmeta-0.0.1.dist-info/top_level.txt
deepmeta-0.0.1.dist-info/RECORD
