Metadata-Version: 2.1
Name: deepmeta
Version: 0.0.1
Summary: deepmeta
Home-page: http://github.com/zhiqingxiao/deepmeta/
Author: Zhiqing Xiao
Author-email: xzq.xiaozhiqing@gmail.com
Classifier: Programming Language :: Python
Classifier: Intended Audience :: Science/Research
